{
  "alignment": [
    "Lawful Good",
    "Neutral Good",
    "Chaotic Good",
    "Lawful Neutral",
    "Neutral",
    "Chaotic Neutral",
    "Lawful Evil",
    "Neutral Evil",
    "Chaotic Evil"
  ],
  "background": [
    "Acolyte",
    "Anthropologist",
    "Archaeologist",
    "Athlete",
    "Charlatan",
    "City Watch",
    "Clan Crafter",
    "Cloistered Scholar",
    "Courtier",
    "Criminal",
    "Entertainer",
    "Far Traveler",
    "Fisher",
    "Folk Hero",
    "Gladiator",
    "Guild Artisan",
    "Guild Merchant",
    "Hermit",
    "Inheritor",
    "Investigator",
    "Knight",
    "Marine",
    "Mercenary Veteran",
    "Noble",
    "Outlander",
    "Pirate",
    "Sage",
    "Sailor",
    "Shipwright",
    "Smuggler",
    "Soldier",
    "Spy",
    "Urban Bounty Hunter",
    "Urchin"
  ],
  "class": [
    "Artificer (#artificer#)",
    "Barbarian (Path of #barbarian#)",
    "Bard (College of #bard#)",
    "Blood Hunter (Order of the #bh#)",
    "Cleric (#cleric# Domain)",
    "Druid (Circle of #druid#)",
    "Fighter (#fighter#)",
    "Monk (Way of #monk#)",
    "Paladin (#paladin#)",
    "Ranger (#ranger#)",
    "Rogue (#rogue#)",
    "Sorcerer (#sorcerer#)",
    "Warlock (The #warlock#)",
    "Wizard (#wizard#)"
  ],
  "artificer": [
    "Alchemist",
    "Armorer",
    "Artillerist",
    "Battle Smith"
  ],
  "barbarian": [
    "the Ancestral Guardian",
    "the Battlerager",
    "the Beast",
    "the Berserker",
    "the Storm Herald",
    "the Totem Warrior",
    "the Zealot",
    "Wild Magic"
  ],
  "bard": [
    "Creation",
    "Eloquence",
    "Glamour",
    "Lore",
    "Spirits",
    "Swords",
    "Valor",
    "Whispers"
  ],
  "bh": [
    "Ghostslayer",
    "Lycan",
    "Mutant",
    "Profane Soul"
  ],
  "cleric": [
    "Arcana",
    "Death",
    "Forge",
    "Grave",
    "Knowledge",
    "Life",
    "Light",
    "Nature",
    "Order",
    "Peace",
    "Tempest",
    "Trickery",
    "Twilight",
    "War"
  ],
  "druid": [
    "Dreams",
    "Spores",
    "Stars",
    "the Land",
    "the Moon",
    "the Shepherd",
    "the Wildfire"
  ],
  "fighter": [
    "Arcane Archer",
    "Battle Master",
    "Cavalier",
    "Champion",
    "Echo Knight",
    "Eldritch Knight",
    "Gunslinger",
    "Psi Warrior",
    "Purple Dragon Knight",
    "Rune Knight",
    "Samurai"
  ],
  "monk": [
    "Mercy",
    "Shadow",
    "the Ascendant Dragon",
    "the Astral Self",
    "the Drunken Master",
    "the Four Elements",
    "the Kensei",
    "the Long Death",
    "the Open Hand",
    "the Sun Soul"
  ],
  "paladin": [
    "Oath of Conquest",
    "Oath of Devotion",
    "Oath of Glory",
    "Oath of Redemption",
    "Oath of the Ancients",
    "Oath of the Crown",
    "Oath of the Open Sea",
    "Oath of the Watchers",
    "Oath of Vengeance",
    "Oathbreaker"
  ],
  "ranger": [
    "Beast Master",
    "Drakewarden",
    "Fey Wanderer",
    "Gloom Stalker",
    "Horizon Walker",
    "Hunter",
    "Monster Slayer",
    "Swarmkeeper"
  ],
  "rogue": [
    "Arcane Trickster",
    "Inquisitive",
    "Mastermind",
    "Phantom",
    "Scout",
    "Soulknife",
    "Swashbuckler",
    "Thief"
  ],
  "sorcerer": [
    "Abberant Mind",
    "Clockwork Soul",
    "Divine Soul",
    "Draconic Bloodline",
    "Shadow Magic",
    "Storm Sorcery",
    "Wild Magic"
  ],
  "warlock": [
    "Archfey",
    "Celestial",
    "Fathomless",
    "Fiend",
    "Genie",
    "Great Old One",
    "Hexblade",
    "Undead",
    "Undying"
  ],
  "wizard": [
    "Bladesinging",
    "Chronurgy Magic",
    "Graviturgy Magic",
    "School of Abjuration",
    "School of Conjuration",
    "School of Divination",
    "School of Enchantment",
    "School of Evocation",
    "School of Illusion",
    "School of Necromancy",
    "School of Transmutation",
    "War Magic"
  ],
  "origin": [
    "#race# #class# - #background# background"
  ],
  "Elf": [
    "High Elf",
    "Drow",
    "Eladrin",
    "Sea Elf",
    "Shadar-Kai",
    "Wood Elf"
  ],
  "race": [
    "Aarakocra",
    "#Aasimar# Aasimar",
    "Bugbear",
    "Centaur",
    "Changeling",
    "Dhampir",
    "#Dragonborn#Dragonborn",
    "#Dwarf#",
    "#Elf#",
    "Fairy",
    "Firbolg",
    "#Genasi# Genasi",
    "Githyanki",
    "Githzerai",
    "#Gnome# Gnome",
    "Goblin",
    "Goliath",
    "Grung",
    "#Halfelf#Half-Elf",
    "Half-Orc",
    "#Halfling# Halfling",
    "Harengon",
    "Hexblood",
    "Hobgoblin",
    "Human",
    "Kalashtar",
    "Kenku",
    "Kobold",
    "Leonin",
    "Lizardfolk",
    "Locathah",
    "Loxodon",
    "Minotaur",
    "Orc",
    "Owlin",
    "Reborn",
    "Satyr",
    "#Shifter# Shifter",
    "Simic Hybrid",
    "Tabaxi",
    "#Tiefling#Tiefling",
    "Tortle",
    "Triton",
    "Vedalken",
    "Verdan",
    "Warforged",
    "Yuan-Ti"
  ],
  "Aasimar": [
    "Fallen",
    "Protector",
    "Scourge"
  ],
  "Dragonborn": [
    "",
    "Chromatic ",
    "Metallic ",
    "Gem "
  ],
  "Dwarf": [
    "Gray Dwarf (Duergar)",
    "Hill Dwarf",
    "Mountain Dwarf"
  ],
  "Halfelf": [
    "",
    "Aquatic ",
    "Drow ",
    "High ",
    "Wood "
  ],
  "Genasi": [
    "Air",
    "Earth",
    "Fire",
    "Water"
  ],
  "Gnome": [
    "Deep",
    "Forest",
    "Rock"
  ],
  "Halfling": [
    "Lightfoot",
    "Stout"
  ],
  "Shifter": [
    "Beasthide",
    "Longtooth",
    "Swiftstride",
    "Wildhunt"
  ],
  "Tiefling": [
    "",
    "Baalzebul ",
    "Dispater ",
    "Fierna ",
    "Glasya ",
    "Levistus ",
    "Mammon ",
    "Mephistopheles ",
    "Variant (Devil's Toungue) ",
    "Variant (Hellfire) ",
    "Variant (Winged) ",
    "Zariel "
  ]
}
